[
  {
    "order_id": "cs_test_a1qxxiyPEp9a4YJBUFuf4xtjUs1cQrpkwwE0Qm0UsqtMDv4J4LnckX9sim",
    "created": 1694613983,
    "customer": {
      "id": "cus_OcSOPmXf7AcCz4",
      "name": "Therese Linden",
      "email": "therese@therese.se"
    },
    "products": [
      {
        "product_id": "prod_OZqJVZlnJ0XWie",
        "product_name": "T-shirt",
        "product_image": "https://files.stripe.com/links/MDB8YWNjdF8xTm1YOUhKTTdyVEljbFh2fGZsX3Rlc3RfSkZjRUg2Ylp5cWJNUkV2RHh0UEJRQ0pZ00MW6iHcjL",
        "price": 34900,
        "quantity": 1,
        "discount": 0,
        "total_price": 34900
      }
    ],
    "amount_total": 34900
  },
  {
    "order_id": "cs_test_a196Rvn5yX0oMRRNB8Gvbu10MhXqpIKvVfKaDcsGulgjyY2rz1HYQbQljA",
    "created": 1694628834,
    "customer": {
      "id": "cus_OcirphVqAo2hyE",
      "name": "Test Test",
      "email": "test@test.se"
    },
    "products": [
      {
        "product_id": "prod_OZqJVZlnJ0XWie",
        "product_name": "T-shirt",
        "product_image": "https://files.stripe.com/links/MDB8YWNjdF8xTm1YOUhKTTdyVEljbFh2fGZsX3Rlc3RfSkZjRUg2Ylp5cWJNUkV2RHh0UEJRQ0pZ00MW6iHcjL",
        "price": 34900,
        "quantity": 2,
        "discount": 0,
        "total_price": 69800
      }
    ],
    "amount_total": 69800
  },
  {
    "order_id": "cs_test_b1wsMBSnuFWFv1eIo3BmDMNLdFSMeR1iIgdn9aq8N4WTdhsTvBtMVCDB6q",
    "created": 1694629726,
    "customer": {
      "id": "cus_OcirphVqAo2hyE",
      "name": "Test Test",
      "email": "test@test.se"
    },
    "products": [
      {
        "product_id": "prod_OZqMlDeukD4OGI",
        "product_name": "Cap",
        "product_image": "https://files.stripe.com/links/MDB8YWNjdF8xTm1YOUhKTTdyVEljbFh2fGZsX3Rlc3RfRUlQbWVtaUp4Qk5lZ3hsYk9hUkhOQVJT00JwoRXSKB",
        "price": 22950,
        "quantity": 1,
        "discount": 4590,
        "total_price": 18360
      }
    ],
    "amount_total": 18360
  }
]